qalgo/__init__.py
qalgo/utils.py
qalgo/wrapper.py
qalgo/qda/__init__.py
qalgo/qda/fundamental.py
qalgo/qda/qram.py
qalgo-0.1.2.dist-info/METADATA
qalgo-0.1.2.dist-info/WHEEL
qalgo-0.1.2.dist-info/licenses/LICENSE
qalgo-0.1.2.dist-info/RECORD
