Metadata-Version: 2.4
Name: qalgo
Version: 0.1.2
Summary: A package for implementing quantum algorithms using the pysparq package.
Project-URL: Repository, https://github.com/TMYTiMidlY/QuantumAlgorithm.git
Author-email: TiMidlY <mytan@mail.ustc.edu.cn>
License-Expression: Apache-2.0
License-File: LICENSE
Keywords: algorithm,pysparq,quantum
Classifier: Development Status :: 4 - Beta
Classifier: Intended Audience :: Developers
Classifier: Intended Audience :: Science/Research
Classifier: License :: OSI Approved :: Apache Software License
Classifier: Operating System :: MacOS
Classifier: Operating System :: Microsoft :: Windows
Classifier: Operating System :: POSIX :: Linux
Classifier: Programming Language :: Python
Classifier: Programming Language :: Python :: 3
Classifier: Programming Language :: Python :: 3 :: Only
Classifier: Programming Language :: Python :: 3.10
Classifier: Programming Language :: Python :: 3.11
Classifier: Programming Language :: Python :: 3.12
Classifier: Programming Language :: Python :: 3.13
Classifier: Topic :: Scientific/Engineering :: Quantum Computing
Classifier: Topic :: Software Development
Classifier: Typing :: Typed
Requires-Python: >=3.10
Requires-Dist: pysparq>=0.0.2
Requires-Dist: scipy
